shell_source/__init__.py
shell_source/py.typed
shell_source/scripters/__init__.py
shell_source/scripters/csh_scripter.py
shell_source/scripters/fish_scripter.py
shell_source/scripters/scripter.py
shell_source/source.py
shell_source-3.0.0.dist-info/LICENSE
shell_source-3.0.0.dist-info/METADATA
shell_source-3.0.0.dist-info/WHEEL
shell_source-3.0.0.dist-info/RECORD
