Metadata-Version: 2.1
Name: shell-source
Version: 3.0.0
Summary: A python module for sourcing variables from shell scripts
Home-page: https://github.com/abrahammurciano/python-shell-source
License: MIT
Keywords: shell,source,environment
Author: Abraham Murciano
Author-email: abrahammurciano@gmail.com
Requires-Python: >=3.7,<4.0
Classifier: License :: OSI Approved :: MIT License
Classifier: Programming Language :: Python :: 3
Classifier: Programming Language :: Python :: 3.7
Classifier: Programming Language :: Python :: 3.8
Classifier: Programming Language :: Python :: 3.9
Classifier: Programming Language :: Python :: 3.10
Classifier: Programming Language :: Python :: 3.11
Requires-Dist: importlib-metadata (>=4.11.4,<5.0.0)
Requires-Dist: toml (>=0.10.2,<0.11.0)
Project-URL: Documentation, https://abrahammurciano.github.io/python-shell-source/shell_source/
Project-URL: Repository, https://github.com/abrahammurciano/python-shell-source
